md2conf/__init__.py
md2conf/__main__.py
md2conf/api.py
md2conf/application.py
md2conf/converter.py
md2conf/entities.dtd
md2conf/mermaid.py
md2conf/processor.py
md2conf/properties.py
md2conf/py.typed
hemstreet_markdown_to_confluence-0.1.15.dist-info/LICENSE
hemstreet_markdown_to_confluence-0.1.15.dist-info/METADATA
hemstreet_markdown_to_confluence-0.1.15.dist-info/WHEEL
hemstreet_markdown_to_confluence-0.1.15.dist-info/entry_points.txt
hemstreet_markdown_to_confluence-0.1.15.dist-info/top_level.txt
hemstreet_markdown_to_confluence-0.1.15.dist-info/zip-safe
hemstreet_markdown_to_confluence-0.1.15.dist-info/RECORD
