Metadata-Version: 2.1
Name: hemstreet-markdown-to-confluence
Version: 0.1.15
Summary: Publish Markdown files to Confluence wiki
Home-page: https://github.com/hunyadi/md2conf
Author: Levente Hunyadi
Author-email: hunyadi@gmail.com
License: MIT
Classifier: Development Status :: 5 - Production/Stable
Classifier: Environment :: Console
Classifier: Intended Audience :: End Users/Desktop
Classifier: License :: OSI Approved :: MIT License
Classifier: Operating System :: OS Independent
Classifier: Programming Language :: Python :: 3
Classifier: Programming Language :: Python :: 3.8
Classifier: Programming Language :: Python :: 3.9
Classifier: Programming Language :: Python :: 3.10
Classifier: Programming Language :: Python :: 3.11
Classifier: Programming Language :: Python :: 3.12
Classifier: Typing :: Typed
Requires-Python: >=3.8
License-File: LICENSE
Requires-Dist: lxml>=5.3
Requires-Dist: types-lxml>=2024.8.7
Requires-Dist: markdown>=3.6
Requires-Dist: types-markdown>=3.6
Requires-Dist: pymdown-extensions>=10.9
Requires-Dist: requests>=2.32
Requires-Dist: types-requests>=2.32
